doraemon_hub-0.2.dist-info/METADATA
doraemon_hub-0.2.dist-info/RECORD
doraemon_hub-0.2.dist-info/WHEEL
doraemon_hub-0.2.dist-info/entry_points.txt
doraemon_hub-0.2.dist-info/top_level.txt
doraemon_hub-0.2.dist-info/zip-safe
rfhub/__init__.py
rfhub/__main__.py
rfhub/app.py
rfhub/kwdb.py
rfhub/version.py
rfhub/blueprints/__init__.py
rfhub/blueprints/api/__init__.py
rfhub/blueprints/api/keywords.py
rfhub/blueprints/api/libraries.py
rfhub/blueprints/dashboard/__init__.py
rfhub/blueprints/dashboard/templates/dashboard.html
rfhub/blueprints/doc/__init__.py
rfhub/blueprints/doc/static/doc.css
rfhub/blueprints/doc/static/doc.js
rfhub/blueprints/doc/templates/base.html
rfhub/blueprints/doc/templates/home.html
rfhub/blueprints/doc/templates/library.html
rfhub/blueprints/doc/templates/libraryNames.html
rfhub/blueprints/doc/templates/search.html
rfhub/blueprints/doc/templates/twocolumn.html
rfhub/static/favicon.ico
rfhub/static/css/bootstrap.min.css
rfhub/static/fonts/glyphicons-halflings-regular.eot
rfhub/static/fonts/glyphicons-halflings-regular.svg
rfhub/static/fonts/glyphicons-halflings-regular.ttf
rfhub/static/fonts/glyphicons-halflings-regular.woff
rfhub/static/js/bootstrap.js
rfhub/static/js/bootstrap.min.js
rfhub/static/js/jquery.min.js
rfhub/static/js/lodash.min.js
rfhub/static/js/query-string.js
