Metadata-Version: 2.1
Name: doraemon-hub
Version: 0.2
Summary: Webserver for robot framework assets
Home-page: https://github.com/boakley/robotframework-hub/
Author: Bryan Oakley
Author-email: bryan.oakley@gmail.com
License: Apache License 2.0
Keywords: doraemon
Platform: UNKNOWN
Classifier: Development Status :: 4 - Beta
Classifier: License :: OSI Approved :: Apache Software License
Classifier: Operating System :: OS Independent
Classifier: Framework :: Robot Framework
Classifier: Programming Language :: Python
Classifier: Topic :: Software Development :: Testing
Classifier: Topic :: Software Development :: Quality Assurance
Classifier: Intended Audience :: Developers
Requires-Dist: Flask
Requires-Dist: watchdog
Requires-Dist: robotframework
Requires-Dist: tornado
